{"type":2300,"data":{"_id":"rsDheTWhBPx/asFPaZlwEon","_key":"asFPaZlwEon","_rev":"62269327","created":"2017-04-27 12:09:00","type":"rsDheTWhBPx","updated":"2017-04-27 12:09:00","value":{"backgroundImage":"zwKeIexNFry","blockName":"EN Footer","logo":"inDnJVTvvoi","logoLink":{"navigationNode":"CnuFdSzMnpEB"},"navigationNode":"ZxlWgBmJjSEB","text":{"blocks":[{"depth":0,"entityRanges":[],"inlineStyleRanges":[],"key":"","text":"DU DA GROUP.","type":"header-six"},{"depth":0,"entityRanges":[],"inlineStyleRanges":[],"key":"","text":"Langstrasse 18, 8004 Zürich","type":"unstyled"},{"depth":0,"entityRanges":[],"inlineStyleRanges":[],"key":"","text":"","type":"unstyled"},{"depth":0,"entityRanges":[],"inlineStyleRanges":[],"key":"","text":"+41 377 88 55","type":"unstyled"},{"depth":0,"entityRanges":[],"inlineStyleRanges":[],"key":"","text":"info@dudagroup.com","type":"unstyled"}],"entityMap":{"0":{"data":{"document":"XtUaazIicYBB"},"mutability":"MUTABLE","type":"LINK"},"1":{"data":{"url":"http://www.dudagroup.com"},"mutability":"MUTABLE","type":"LINK"},"2":{"data":{"navigationNode":"CnuFdSzMnpEB"},"mutability":"MUTABLE","type":"LINK"}}}}}}
{"type":2300,"data":{"_id":"rsDheTWhBPx/djFmWXwkssDB","_key":"djFmWXwkssDB","_rev":"62269401","created":"2017-04-27 12:09:00","type":"rsDheTWhBPx","updated":"2017-04-27 12:09:00","value":{"backgroundImage":"zwKeIexNFry","blockName":"DE Footer","logo":"inDnJVTvvoi","logoLink":{"navigationNode":"CnuFdSzMnpEB"},"navigationNode":"GQCtYbfuPCe","text":{"blocks":[{"depth":0,"entityRanges":[],"inlineStyleRanges":[],"key":"","text":"DU DA GROUP.","type":"header-six"},{"depth":0,"entityRanges":[],"inlineStyleRanges":[],"key":"","text":"Langstrasse 18, 8004 Zürich","type":"unstyled"},{"depth":0,"entityRanges":[],"inlineStyleRanges":[],"key":"","text":"","type":"unstyled"},{"depth":0,"entityRanges":[],"inlineStyleRanges":[],"key":"","text":"+41 377 88 55","type":"unstyled"},{"depth":0,"entityRanges":[],"inlineStyleRanges":[],"key":"","text":"info@dudagroup.com","type":"unstyled"}],"entityMap":{"0":{"data":{"document":"XtUaazIicYBB"},"mutability":"MUTABLE","type":"LINK"},"1":{"data":{"url":"http://www.dudagroup.com"},"mutability":"MUTABLE","type":"LINK"},"2":{"data":{"navigationNode":"CnuFdSzMnpEB"},"mutability":"MUTABLE","type":"LINK"}}}}}}
