{"type":2300,"data":{"_id":"wmaxXtdMVCx/ZqbbykxYFkd","_key":"ZqbbykxYFkd","_rev":"70223757","created":"2017-06-21 09:22:08","type":"wmaxXtdMVCx","updated":"2017-06-21 09:22:08","value":{"blockName":"EN Big Data","contents":[{"blockHeader":"xvgVXMPEjIm"},{"blockImageSlider":"FiQolHcBjYO"},{"blockRichText":"xuPFDjtcTUJ"},{"blockTitle":"qXQlAVdxYuBB"}],"description":"Description Home","expiryDate":0,"isLive":true,"navigationNode":"YepWArvvGNCB","publishDate":0,"shareImage":"jAfLyMCaaKq","tags":["Big Data","duda group"],"title":"Big Data"}}}
{"type":2300,"data":{"_id":"wmaxXtdMVCx/pCbOFHfqzpT","_key":"pCbOFHfqzpT","_rev":"70223788","created":"2017-06-21 09:22:08","type":"wmaxXtdMVCx","updated":"2017-06-21 09:22:08","value":{"blockName":"EN Hybrid Consulting","contents":[{"blockHeader":"xvgVXMPEjIm"},{"blockTitle":"kqCJYhPzexn"},{"blockRichText":"xuPFDjtcTUJ"}],"description":"Description Home","expiryDate":0,"isLive":true,"navigationNode":"btZdcvCxPst","publishDate":0,"shareImage":"jAfLyMCaaKq","tags":["Hybrid Consulting","duda group"],"title":"Hybrid Consulting"}}}
{"type":2300,"data":{"_id":"wmaxXtdMVCx/JygdimHdIjb","_key":"JygdimHdIjb","_rev":"70223852","created":"2017-06-21 09:22:08","type":"wmaxXtdMVCx","updated":"2017-06-21 09:22:08","value":{"blockName":"EN Contact","contents":[{"blockHeader":"xvgVXMPEjIm"},{"blockTitle":"sgVRPMsHscm"},{"blockImageSlider":"FiQolHcBjYO"},{"blockRichText":"xuPFDjtcTUJ"},{"blockTeaserSpot":"xFKseyRVcdg"}],"description":"Description Home","expiryDate":0,"isLive":true,"navigationNode":"gbVyZYdjZWi","publishDate":0,"shareImage":"jAfLyMCaaKq","tags":["Contact","duda group"],"title":"Contact"}}}
{"type":2300,"data":{"_id":"wmaxXtdMVCx/LQkmfZMJpve","_key":"LQkmfZMJpve","_rev":"70223877","created":"2017-06-21 09:22:08","type":"wmaxXtdMVCx","updated":"2017-06-21 09:22:08","value":{"blockName":"EN About","contents":[{"blockHeader":"xvgVXMPEjIm"},{"blockTitle":"edzTjtGawqP"},{"blockTeaserSpot":"xFKseyRVcdg"}],"description":"Description Home","expiryDate":0,"isLive":true,"navigationNode":"azGhfIYvlIU","publishDate":0,"shareImage":"jAfLyMCaaKq","tags":["About","duda group"],"title":"About"}}}
{"type":2300,"data":{"_id":"wmaxXtdMVCx/DKsLiUUFVcE","_key":"DKsLiUUFVcE","_rev":"70241927","created":"2017-06-21 09:22:08","type":"wmaxXtdMVCx","updated":"2017-06-21 12:08:52","value":{"blockName":"EN Micro Services","contents":[{"blockHeader":"xvgVXMPEjIm"},{"blockWebsiteTeaser":"FmRHDIoVqxv"},{"blockTitle":"PIOvXLiWdKM"},{"blockTeaserSpot":"xFKseyRVcdg"},{"blockRichText":"xuPFDjtcTUJ"}],"description":"Description Home","expiryDate":0,"isLive":true,"navigationNode":"tgGaiAhzBGIB","publishDate":0,"shareImage":"jAfLyMCaaKq","tags":["Micro Services","duda group"],"title":"Micro Services"}}}
