{"type":2300,"data":{"_id":"YxvRSuHcdfLB/VXYbuBRoTAU","_key":"VXYbuBRoTAU","_rev":"69869566","created":"2017-06-19 07:55:40","type":"YxvRSuHcdfLB","updated":"2017-06-19 07:55:40","value":{"backgroundImage":"grhrfMriDtI","blockName":"Duda Group Header","logo":"UnyaVXRSHtS","title":{"blocks":[{"depth":0,"entityRanges":[],"inlineStyleRanges":[],"key":"","text":"We Do.","type":"header-two"},{"depth":0,"entityRanges":[],"inlineStyleRanges":[{"length":150,"offset":0,"style":"BOLD"}],"key":"","text":"Digital Business.","type":"header-one"}],"entityMap":{"0":{"data":{"document":"grhrfMriDtI"},"mutability":"MUTABLE","type":"LINK"},"1":{"data":{"url":"http://www.dudagroup.com"},"mutability":"MUTABLE","type":"LINK"},"2":{"data":{"navigationNode":"nbHivKRXEMFB"},"mutability":"MUTABLE","type":"LINK"}}}}}}
